{
  "additions": 5,
  "assignees": [],
  "author": {
    "id": "MDQ6VXNlcjI4ODExNzIw",
    "is_bot": false,
    "login": "tmedicci",
    "name": "Tiago Medicci Serrano"
  },
  "autoMergeRequest": null,
  "baseRefName": "master",
  "changedFiles": 1,
  "closed": true,
  "closedAt": "2025-04-09T06:00:08Z",
  "createdAt": "2025-04-08T16:52:11Z",
  "deletions": 5,
  "files": [
    {
      "path": "arch/xtensa/src/common/espressif/Kconfig",
      "additions": 5,
      "deletions": 5
    }
  ],
  "headRefName": "bugfix/esp32s2_spi_flash_freq_selection",
  "headRefOid": "8a934238447c81982eb8fb5d4ae0d02e286d0d5d",
  "headRepository": {
    "id": "R_kgDOHwFqQQ",
    "name": "nuttx"
  },
  "headRepositoryOwner": {
    "id": "MDQ6VXNlcjI4ODExNzIw",
    "name": "Tiago Medicci Serrano",
    "login": "tmedicci"
  },
  "id": "PR_kwDODZiUac6R0esY",
  "isDraft": false,
  "labels": [
    {
      "id": "LA_kwDODZiUac8AAAABsqRKYw",
      "name": "Arch: xtensa",
      "description": "Issues related to the Xtensa architecture",
      "color": "DC5544"
    },
    {
      "id": "LA_kwDODZiUac8AAAABvj_XyQ",
      "name": "Size: S",
      "description": "The size of the change in this PR is small",
      "color": "FEF2C0"
    }
  ],
  "mergeCommit": {
    "oid": "05e63e31c4834013f3a23cbe0b9da44abd9a7afe"
  },
  "mergeStateStatus": "UNKNOWN",
  "mergeable": "UNKNOWN",
  "mergedAt": "2025-04-09T06:00:08Z",
  "mergedBy": {
    "id": "MDQ6VXNlcjE4MDY2OTY0",
    "is_bot": false,
    "login": "xiaoxiang781216",
    "name": "Xiang Xiao"
  },
  "milestone": null,
  "number": 16157,
  "state": "MERGED",
  "title": "arch/xtensa/espressif: Fix ESP32-S2 SPI flash frequency selection",
  "updatedAt": "2025-04-09T06:00:09Z",
  "url": "https://github.com/apache/nuttx/pull/16157"
}
