{
  "additions": 41,
  "assignees": [],
  "author": {
    "id": "MDQ6VXNlcjI4ODExNzIw",
    "is_bot": false,
    "login": "tmedicci",
    "name": "Tiago Medicci Serrano"
  },
  "autoMergeRequest": null,
  "baseRefName": "master",
  "changedFiles": 3,
  "closed": true,
  "closedAt": "2025-06-22T06:57:11Z",
  "createdAt": "2025-06-20T18:10:00Z",
  "deletions": 2,
  "files": [
    {
      "path": "Documentation/platforms/risc-v/qemu-rv/boards/rv-virt/index.rst",
      "additions": 33,
      "deletions": 0
    },
    {
      "path": "arch/risc-v/src/common/riscv_swint.c",
      "additions": 2,
      "deletions": 2
    },
    {
      "path": "boards/risc-v/qemu-rv/rv-virt/scripts/ld-nuttsbi.script",
      "additions": 6,
      "deletions": 0
    }
  ],
  "headRefName": "bugfix/fix_rv-virt_nsbi",
  "headRefOid": "2ec6fcc3ea53f8b46ff8e027c4b57c3f2af41534",
  "headRepository": {
    "id": "R_kgDOHwFqQQ",
    "name": "nuttx"
  },
  "headRepositoryOwner": {
    "id": "MDQ6VXNlcjI4ODExNzIw",
    "name": "Tiago Medicci Serrano",
    "login": "tmedicci"
  },
  "id": "PR_kwDODZiUac6bdR8F",
  "isDraft": false,
  "labels": [
    {
      "id": "MDU6TGFiZWwxNzM0NzM5NDI0",
      "name": "Area: Documentation",
      "description": "Improvements or additions to documentation",
      "color": "0075ca"
    },
    {
      "id": "LA_kwDODZiUac8AAAABsqQhgw",
      "name": "Arch: risc-v",
      "description": "Issues related to the RISC-V (32-bit or 64-bit) architecture",
      "color": "DC5544"
    },
    {
      "id": "LA_kwDODZiUac8AAAABvj_XyQ",
      "name": "Size: S",
      "description": "The size of the change in this PR is small",
      "color": "FEF2C0"
    },
    {
      "id": "LA_kwDODZiUac8AAAABw8L77A",
      "name": "Board: risc-v",
      "description": "",
      "color": "F9D0C4"
    }
  ],
  "mergeCommit": {
    "oid": "b3712797faf5ea00d2146751d740503aac3b630a"
  },
  "mergeStateStatus": "UNKNOWN",
  "mergeable": "UNKNOWN",
  "mergedAt": "2025-06-22T06:57:11Z",
  "mergedBy": {
    "id": "MDQ6VXNlcjE4MDY2OTY0",
    "is_bot": false,
    "login": "xiaoxiang781216",
    "name": "Xiang Xiao"
  },
  "milestone": null,
  "number": 16565,
  "state": "MERGED",
  "title": "arch/risc-v: Fix `rv-virt:nsbi[|64]` defconfigs",
  "updatedAt": "2025-06-22T06:57:11Z",
  "url": "https://github.com/apache/nuttx/pull/16565"
}
