{
  "additions": 7,
  "assignees": [],
  "author": {
    "id": "U_kgDOCqsAKA",
    "is_bot": false,
    "login": "OceanfromXiaomi",
    "name": ""
  },
  "autoMergeRequest": null,
  "baseRefName": "master",
  "changedFiles": 2,
  "closed": true,
  "closedAt": "2026-01-07T07:31:06Z",
  "createdAt": "2026-01-06T11:57:34Z",
  "deletions": 7,
  "files": [
    {
      "path": "net/can/can.h",
      "additions": 4,
      "deletions": 4
    },
    {
      "path": "net/can/can_callback.c",
      "additions": 3,
      "deletions": 3
    }
  ],
  "headRefName": "modify_return_value_can_datahandler",
  "headRefOid": "ca775d7ca7618216af8bd740ad50a88682b81a98",
  "headRepository": {
    "id": "R_kgDOMmOEBQ",
    "name": "nuttx-kernel"
  },
  "headRepositoryOwner": {
    "id": "U_kgDOCqsAKA",
    "login": "OceanfromXiaomi"
  },
  "id": "PR_kwDODZiUac67tYFg",
  "isDraft": false,
  "labels": [
    {
      "id": "MDU6TGFiZWwyNTEzMzUyMDMz",
      "name": "Area: Networking",
      "description": "Effects networking subsystem",
      "color": "0075ca"
    },
    {
      "id": "LA_kwDODZiUac8AAAABvj_XyQ",
      "name": "Size: S",
      "description": "The size of the change in this PR is small",
      "color": "FEF2C0"
    }
  ],
  "mergeCommit": {
    "oid": "f53b986fb2042b5090fe29f8516243b67aafc6e1"
  },
  "mergeStateStatus": "UNKNOWN",
  "mergeable": "UNKNOWN",
  "mergedAt": "2026-01-07T07:31:06Z",
  "mergedBy": {
    "id": "MDQ6VXNlcjY4OTk4NTQz",
    "is_bot": false,
    "login": "michallenc",
    "name": "Michal Lenc"
  },
  "milestone": null,
  "number": 17775,
  "state": "MERGED",
  "title": "net can: modify the return value of can_datahandler API.",
  "updatedAt": "2026-01-07T07:31:06Z",
  "url": "https://github.com/apache/nuttx/pull/17775"
}
