{
  "additions": 2,
  "assignees": [],
  "author": {
    "id": "MDQ6VXNlcjY4NzI5MzM3",
    "is_bot": false,
    "login": "ThePassionate",
    "name": "makejian"
  },
  "autoMergeRequest": null,
  "baseRefName": "master",
  "changedFiles": 1,
  "closed": true,
  "closedAt": "2026-01-29T14:44:25Z",
  "createdAt": "2026-01-28T15:45:22Z",
  "deletions": 7,
  "files": [
    {
      "path": "boards/sim/sim/sim/configs/crypto/defconfig",
      "additions": 2,
      "deletions": 7
    }
  ],
  "headRefName": "sim-crypto-testing",
  "headRefOid": "186e2b91d5348ac517ec0623ed33b84e4671a4ca",
  "headRepository": {
    "id": "R_kgDOKAa8wg",
    "name": "nuttx"
  },
  "headRepositoryOwner": {
    "id": "MDQ6VXNlcjY4NzI5MzM3",
    "name": "makejian",
    "login": "ThePassionate"
  },
  "id": "PR_kwDODZiUac6_4618",
  "isDraft": false,
  "labels": [
    {
      "id": "LA_kwDODZiUac8AAAABvj_Wkw",
      "name": "Size: XS",
      "description": "The size of the change in this PR is very small",
      "color": "0E8A16"
    },
    {
      "id": "LA_kwDODZiUac8AAAABw8L-Yw",
      "name": "Board: simulator",
      "description": "",
      "color": "F9D0C4"
    }
  ],
  "mergeCommit": {
    "oid": "d9c6353b747aecf2ce1396d08bc3acab88c64fa6"
  },
  "mergeStateStatus": "UNKNOWN",
  "mergeable": "UNKNOWN",
  "mergedAt": "2026-01-29T14:44:25Z",
  "mergedBy": {
    "id": "MDQ6VXNlcjE4MDY2OTY0",
    "is_bot": false,
    "login": "xiaoxiang781216",
    "name": "Xiang Xiao"
  },
  "milestone": null,
  "number": 18251,
  "state": "MERGED",
  "title": "boards/sim/crypto: enable cmocka testing framework",
  "updatedAt": "2026-01-29T14:44:25Z",
  "url": "https://github.com/apache/nuttx/pull/18251"
}
