{
  "attempt": 1,
  "conclusion": "success",
  "createdAt": "2025-03-10T09:41:09Z",
  "databaseId": 13761479312,
  "displayTitle": "cmake: Add utility target to update .config with minimal changes",
  "event": "pull_request",
  "headBranch": "crate",
  "headSha": "1b320f088671813d268054b92027ef352109d528",
  "name": "Lint",
  "number": 32813,
  "startedAt": "2025-03-10T09:41:09Z",
  "status": "completed",
  "updatedAt": "2025-03-10T09:43:13Z",
  "url": "https://github.com/apache/nuttx/actions/runs/13761479312",
  "workflowDatabaseId": 4260298,
  "workflowName": "Lint"
}
