{
  "attempt": 1,
  "conclusion": "success",
  "createdAt": "2025-03-12T07:20:37Z",
  "databaseId": 13805817553,
  "displayTitle": "Documentation/uorb: fix typo in uorb chapter",
  "event": "pull_request",
  "headBranch": "25031201",
  "headSha": "f4e02c467186446bf1a1b78ed403b02e392e96f1",
  "name": "Lint",
  "number": 32840,
  "startedAt": "2025-03-12T07:20:37Z",
  "status": "completed",
  "updatedAt": "2025-03-12T07:22:45Z",
  "url": "https://github.com/apache/nuttx/actions/runs/13805817553",
  "workflowDatabaseId": 4260298,
  "workflowName": "Lint"
}
