{
  "attempt": 1,
  "conclusion": "success",
  "createdAt": "2025-03-12T13:10:19Z",
  "databaseId": 13812173400,
  "displayTitle": "sched/sem_waitirq: Move kmm_map() call to sem_wait()",
  "event": "pull_request",
  "headBranch": "sem_waitirq_kmap_bug",
  "headSha": "e3163ec528f16c249be563d4994663339f9ed337",
  "name": "Lint",
  "number": 32847,
  "startedAt": "2025-03-12T13:10:19Z",
  "status": "completed",
  "updatedAt": "2025-03-12T13:12:25Z",
  "url": "https://github.com/apache/nuttx/actions/runs/13812173400",
  "workflowDatabaseId": 4260298,
  "workflowName": "Lint"
}
