{
  "attempt": 1,
  "conclusion": "success",
  "createdAt": "2025-03-18T22:40:30Z",
  "databaseId": 13934871245,
  "displayTitle": "arch/xtensa/esp32: Add support for hardware accelerated SHA",
  "event": "pull_request_target",
  "headBranch": "esp32_crypto_acc",
  "headSha": "7c251d6340faf0be885c5a5a60903c160f1ec4bf",
  "name": "Pull Request Labeler",
  "number": 5657,
  "startedAt": "2025-03-18T22:40:30Z",
  "status": "completed",
  "updatedAt": "2025-03-18T22:41:02Z",
  "url": "https://github.com/apache/nuttx/actions/runs/13934871245",
  "workflowDatabaseId": 118322422,
  "workflowName": "Pull Request Labeler"
}
