{
  "attempt": 1,
  "conclusion": "success",
  "createdAt": "2025-04-01T10:26:51Z",
  "databaseId": 14193286924,
  "displayTitle": "drivers/lcd/st7789: Send RAMCTRL if little endian",
  "event": "pull_request_target",
  "headBranch": "br_wjy_lcd_st7789_ramctrl_fix_250401",
  "headSha": "4ada453106b97c7bab3c84275d3487ea4a670a6e",
  "name": "Pull Request Labeler",
  "number": 5823,
  "startedAt": "2025-04-01T10:26:51Z",
  "status": "completed",
  "updatedAt": "2025-04-01T10:27:20Z",
  "url": "https://github.com/apache/nuttx/actions/runs/14193286924",
  "workflowDatabaseId": 118322422,
  "workflowName": "Pull Request Labeler"
}
