{
  "conclusion": "success",
  "createdAt": "2025-04-08T06:06:03Z",
  "databaseId": 14326322524,
  "displayTitle": "kernel build:avoid multiple definition ld script",
  "event": "pull_request",
  "headBranch": "20250408_modlib",
  "headSha": "6a54c92193e4cb4bf0a509ab1e33c5413dda52d8",
  "name": "Check",
  "number": 6079,
  "startedAt": "2025-04-08T06:06:03Z",
  "status": "completed",
  "updatedAt": "2025-04-08T06:06:50Z",
  "url": "https://github.com/apache/nuttx-apps/actions/runs/14326322524",
  "workflowDatabaseId": 904465,
  "workflowName": "Check"
}
