{
  "conclusion": "success",
  "createdAt": "2025-04-08T09:48:45Z",
  "databaseId": 14330473969,
  "displayTitle": "arch/xtensa: Add common I2S support for esp32[- |-s2|-s3]",
  "event": "pull_request",
  "headBranch": "feature/esp_xtensa_i2s",
  "headSha": "9d171f3e536a2cc1601a9cbfb37fe94c63f870bc",
  "name": "Lint",
  "number": 33163,
  "startedAt": "2025-04-08T09:48:45Z",
  "status": "completed",
  "updatedAt": "2025-04-08T09:50:51Z",
  "url": "https://github.com/apache/nuttx/actions/runs/14330473969",
  "workflowDatabaseId": 4260298,
  "workflowName": "Lint"
}
