{
  "conclusion": "success",
  "createdAt": "2025-04-09T11:00:00Z",
  "databaseId": 14355468961,
  "displayTitle": "drivers/rpmsg: correct crc16 catalogue to CRC-16/IBM",
  "event": "pull_request",
  "headBranch": "25040901",
  "headSha": "535e4d07911e1d3c22e5c26ac0b53ee90c26901f",
  "name": "Build",
  "number": 48054,
  "startedAt": "2025-04-09T11:00:00Z",
  "status": "completed",
  "updatedAt": "2025-04-09T13:27:14Z",
  "url": "https://github.com/apache/nuttx/actions/runs/14355468961",
  "workflowDatabaseId": 908549,
  "workflowName": "Build"
}
