{
  "conclusion": "failure",
  "createdAt": "2025-04-14T09:52:43Z",
  "databaseId": 14442716435,
  "displayTitle": "net/netdev: Change SIOCSCANBITRATE to require interface down.",
  "event": "pull_request",
  "headBranch": "SIOCSCANBITRATE_no_ifup",
  "headSha": "890407332605126842ef0823f2a792b1a4e8f1d0",
  "name": "Check",
  "number": 36525,
  "startedAt": "2025-04-14T09:52:43Z",
  "status": "completed",
  "updatedAt": "2025-04-14T09:53:26Z",
  "url": "https://github.com/apache/nuttx/actions/runs/14442716435",
  "workflowDatabaseId": 904371,
  "workflowName": "Check"
}
