{
  "conclusion": "success",
  "createdAt": "2025-04-14T21:34:15Z",
  "databaseId": 14456229965,
  "displayTitle": "arch/arm/stm32h5: Fix i2c compiler warnings.",
  "event": "pull_request",
  "headBranch": "h5-i2c",
  "headSha": "330fd4acfe0b5c4f0fb845cb0a296324729c04eb",
  "name": "Build",
  "number": 48129,
  "startedAt": "2025-04-14T21:34:15Z",
  "status": "completed",
  "updatedAt": "2025-04-14T23:18:51Z",
  "url": "https://github.com/apache/nuttx/actions/runs/14456229965",
  "workflowDatabaseId": 908549,
  "workflowName": "Build"
}
