{
  "conclusion": "success",
  "createdAt": "2025-04-17T13:31:24Z",
  "databaseId": 14516871452,
  "displayTitle": "examples/elf: add possibility to create romfs image",
  "event": "pull_request",
  "headBranch": "elfromfs",
  "headSha": "8a5bbd98c5aba1fb3c8624eb8e49362ec2323738",
  "name": "Lint",
  "number": 5384,
  "startedAt": "2025-04-17T18:13:59Z",
  "status": "completed",
  "updatedAt": "2025-04-17T18:15:41Z",
  "url": "https://github.com/apache/nuttx-apps/actions/runs/14516871452",
  "workflowDatabaseId": 4585365,
  "workflowName": "Lint"
}
