{
  "attempt": 1,
  "conclusion": "success",
  "createdAt": "2025-04-27T12:14:37Z",
  "databaseId": 14691930375,
  "displayTitle": "sched/wqueue: Refactor delayed and periodic workqueue.",
  "event": "pull_request",
  "headBranch": "wqueue-fix",
  "headSha": "1356c3a77fbc8cb9d07f71aa1cbaf5c8fd46afad",
  "name": "Lint",
  "number": 33415,
  "startedAt": "2025-04-27T12:14:37Z",
  "status": "completed",
  "updatedAt": "2025-04-27T12:16:42Z",
  "url": "https://github.com/apache/nuttx/actions/runs/14691930375",
  "workflowDatabaseId": 4260298,
  "workflowName": "Lint"
}
