{
  "conclusion": "success",
  "createdAt": "2025-04-29T06:25:06Z",
  "databaseId": 14724739974,
  "displayTitle": "[BREAKING] setlogmask: fix setlogmask behavior according to POSIX standard",
  "event": "pull_request_target",
  "headBranch": "syslog-fix",
  "headSha": "d56373ae708aa883c088998fb45752cf244ef9ac",
  "name": "Pull Request Labeler",
  "number": 6203,
  "startedAt": "2025-04-29T06:25:06Z",
  "status": "completed",
  "updatedAt": "2025-04-29T06:25:39Z",
  "url": "https://github.com/apache/nuttx/actions/runs/14724739974",
  "workflowDatabaseId": 118322422,
  "workflowName": "Pull Request Labeler"
}
