{
  "conclusion": "cancelled",
  "createdAt": "2025-05-06T03:13:15Z",
  "databaseId": 14850846196,
  "displayTitle": "sched/wqueue: Refactor delayed and periodic workqueue.",
  "event": "pull_request",
  "headBranch": "wqueue-fix",
  "headSha": "38b21ee7b1810b1ea06ef395484c20bd40ce039d",
  "name": "Build",
  "number": 48406,
  "startedAt": "2025-05-06T03:13:15Z",
  "status": "completed",
  "updatedAt": "2025-05-06T03:25:11Z",
  "url": "https://github.com/apache/nuttx/actions/runs/14850846196",
  "workflowDatabaseId": 908549,
  "workflowName": "Build"
}
