{
  "attempt": 1,
  "conclusion": "success",
  "createdAt": "2025-05-07T03:11:12Z",
  "databaseId": 14874286341,
  "displayTitle": "sched/queue: fix typo in dq_insert_mid macro",
  "event": "pull_request",
  "headBranch": "queuetypo",
  "headSha": "d73e8eb0611e9bf14f2f70cd26964c815dcf8fb6",
  "name": "Check",
  "number": 36842,
  "startedAt": "2025-05-07T03:11:12Z",
  "status": "completed",
  "updatedAt": "2025-05-07T03:11:54Z",
  "url": "https://github.com/apache/nuttx/actions/runs/14874286341",
  "workflowDatabaseId": 904371,
  "workflowName": "Check"
}
