{
  "conclusion": "success",
  "createdAt": "2025-05-08T01:37:36Z",
  "databaseId": 14896733393,
  "displayTitle": "DOCUMENTATION: Migrate READMEs",
  "event": "pull_request",
  "headBranch": "migrate-readmes-2",
  "headSha": "68aabace4fa240c83444ee1699d4fbfe8675a615",
  "name": "Lint",
  "number": 33631,
  "startedAt": "2025-05-08T01:37:36Z",
  "status": "completed",
  "updatedAt": "2025-05-08T01:39:49Z",
  "url": "https://github.com/apache/nuttx/actions/runs/14896733393",
  "workflowDatabaseId": 4260298,
  "workflowName": "Lint"
}
