{
  "conclusion": "success",
  "createdAt": "2025-05-08T07:44:13Z",
  "databaseId": 14901361424,
  "displayTitle": "Adding new example Xedge",
  "event": "pull_request",
  "headBranch": "master",
  "headSha": "055fcfca1719fd857467947cfa9fbe2424e82e3d",
  "name": "Lint",
  "number": 5415,
  "startedAt": "2025-05-08T10:48:28Z",
  "status": "completed",
  "updatedAt": "2025-05-08T10:50:14Z",
  "url": "https://github.com/apache/nuttx-apps/actions/runs/14901361424",
  "workflowDatabaseId": 4585365,
  "workflowName": "Lint"
}
