{
  "attempt": 1,
  "conclusion": "success",
  "createdAt": "2025-05-09T05:09:09Z",
  "databaseId": 14921875559,
  "displayTitle": "arch/arm/rp23xx: remove spinlock from up_txint",
  "event": "pull_request",
  "headBranch": "serialtxint",
  "headSha": "957036d5e0598f19a8feebcfce5dbf1ed8f1165a",
  "name": "Build",
  "number": 48509,
  "startedAt": "2025-05-09T05:09:09Z",
  "status": "completed",
  "updatedAt": "2025-05-09T06:51:44Z",
  "url": "https://github.com/apache/nuttx/actions/runs/14921875559",
  "workflowDatabaseId": 908549,
  "workflowName": "Build"
}
