{
  "attempt": 1,
  "conclusion": "success",
  "createdAt": "2025-05-12T02:15:56Z",
  "databaseId": 14962362315,
  "displayTitle": "github_actions in /. - Update #1013713902",
  "event": "dynamic",
  "headBranch": "master",
  "headSha": "b05ec7729d9b7fe85a6f11bfbb2da979255f44b7",
  "name": "github_actions in /. - Update #1013713902",
  "number": 29,
  "startedAt": "2025-05-12T02:15:56Z",
  "status": "completed",
  "updatedAt": "2025-05-12T02:16:50Z",
  "url": "https://github.com/apache/nuttx/actions/runs/14962362315",
  "workflowDatabaseId": 132114829,
  "workflowName": "Dependabot Updates"
}
