{
  "conclusion": "success",
  "createdAt": "2025-05-14T04:13:47Z",
  "databaseId": 15012105234,
  "displayTitle": "libc/fdcheck: fix issue about  a double close check",
  "event": "pull_request",
  "headBranch": "fdcheck",
  "headSha": "13c9a680086a92a7a102160f6983c14945d0f10b",
  "name": "Lint",
  "number": 33734,
  "startedAt": "2025-05-14T04:13:47Z",
  "status": "completed",
  "updatedAt": "2025-05-14T04:15:52Z",
  "url": "https://github.com/apache/nuttx/actions/runs/15012105234",
  "workflowDatabaseId": 4260298,
  "workflowName": "Lint"
}
