{
  "attempt": 1,
  "conclusion": "success",
  "createdAt": "2025-05-16T13:05:48Z",
  "databaseId": 15069138350,
  "displayTitle": "tools/nxstyle.c: fix error Relative file path on Windows Native",
  "event": "pull_request",
  "headBranch": "simbit18-nxstyle",
  "headSha": "9d313b4f05e39de8546eda0b6d2a65670381c031",
  "name": "Check",
  "number": 37042,
  "startedAt": "2025-05-16T13:05:48Z",
  "status": "completed",
  "updatedAt": "2025-05-16T13:06:32Z",
  "url": "https://github.com/apache/nuttx/actions/runs/15069138350",
  "workflowDatabaseId": 904371,
  "workflowName": "Check"
}
