{
  "attempt": 1,
  "conclusion": "success",
  "createdAt": "2025-05-25T06:30:48Z",
  "databaseId": 15235090643,
  "displayTitle": "adding \"edit on github\" option in docs",
  "event": "pull_request",
  "headBranch": "master",
  "headSha": "2cdff547b06d280fbf6863b611fc30446ef79afa",
  "name": "Build Documentation",
  "number": 45115,
  "startedAt": "2025-05-25T06:30:48Z",
  "status": "completed",
  "updatedAt": "2025-05-25T06:33:07Z",
  "url": "https://github.com/apache/nuttx/actions/runs/15235090643",
  "workflowDatabaseId": 904372,
  "workflowName": "Build Documentation"
}
