{
  "attempt": 1,
  "conclusion": "success",
  "createdAt": "2025-06-10T14:29:55Z",
  "databaseId": 15562328490,
  "displayTitle": "[BREAKING] fs/vfs: Separate file descriptors from file descriptions",
  "event": "pull_request_target",
  "headBranch": "fs_fdlist_rewrite",
  "headSha": "4aaeb809bab26369cb835d65107bdf69152710e1",
  "name": "Pull Request Labeler",
  "number": 6790,
  "startedAt": "2025-06-10T14:29:55Z",
  "status": "completed",
  "updatedAt": "2025-06-10T14:30:31Z",
  "url": "https://github.com/apache/nuttx/actions/runs/15562328490",
  "workflowDatabaseId": 118322422,
  "workflowName": "Pull Request Labeler"
}
