{
  "conclusion": "cancelled",
  "createdAt": "2025-06-22T06:49:48Z",
  "databaseId": 15803938063,
  "displayTitle": "libc: Change atomic_fetch_cxx to macro",
  "event": "pull_request",
  "headBranch": "atomic",
  "headSha": "63b711ef8783a8e227fbae311b88b11e01b4daec",
  "name": "Lint",
  "number": 34154,
  "startedAt": "2025-06-22T06:49:48Z",
  "status": "completed",
  "updatedAt": "2025-06-22T06:50:19Z",
  "url": "https://github.com/apache/nuttx/actions/runs/15803938063",
  "workflowDatabaseId": 4260298,
  "workflowName": "Lint"
}
