{
  "attempt": 1,
  "conclusion": "success",
  "createdAt": "2025-06-26T20:33:21Z",
  "databaseId": 15911905601,
  "displayTitle": "apps/can: Replace fprintf with dprint",
  "event": "pull_request",
  "headBranch": "fix_can_app",
  "headSha": "73336934a5bfe1a333e9428c5cf41600395ce486",
  "name": "Build",
  "number": 8586,
  "startedAt": "2025-06-26T20:33:21Z",
  "status": "completed",
  "updatedAt": "2025-06-26T23:06:30Z",
  "url": "https://github.com/apache/nuttx-apps/actions/runs/15911905601",
  "workflowDatabaseId": 908566,
  "workflowName": "Build"
}
