{
  "attempt": 1,
  "conclusion": "success",
  "createdAt": "2025-07-04T15:55:47Z",
  "databaseId": 16077362061,
  "displayTitle": "boards/qemu-armv8a: Add `xedge` example program and documentation",
  "event": "pull_request_target",
  "headBranch": "master",
  "headSha": "05482c51e2e6756ddc2ddc8b51dd5a8ee5175dd5",
  "name": "Pull Request Labeler",
  "number": 7129,
  "startedAt": "2025-07-04T15:55:47Z",
  "status": "completed",
  "updatedAt": "2025-07-04T15:56:13Z",
  "url": "https://github.com/apache/nuttx/actions/runs/16077362061",
  "workflowDatabaseId": 118322422,
  "workflowName": "Pull Request Labeler"
}
