{
  "conclusion": "success",
  "createdAt": "2025-07-07T09:28:30Z",
  "databaseId": 16113195491,
  "displayTitle": "arch/risc-v: Change DMA functions with common layer for esp32[-c3|-c6|-h2]",
  "event": "pull_request",
  "headBranch": "feature/esp_rv_dma",
  "headSha": "a9a99d2d43152486beda4a9e9f364e1c44dc0dc6",
  "name": "Build",
  "number": 49213,
  "startedAt": "2025-07-07T09:28:30Z",
  "status": "completed",
  "updatedAt": "2025-07-07T10:38:06Z",
  "url": "https://github.com/apache/nuttx/actions/runs/16113195491",
  "workflowDatabaseId": 908549,
  "workflowName": "Build"
}
