{
  "conclusion": "success",
  "createdAt": "2025-07-25T07:01:01Z",
  "databaseId": 16515933461,
  "displayTitle": "drivers/misc/optee: expand RPC suppport for IMX9",
  "event": "pull_request",
  "headBranch": "imx9-optee-rpc",
  "headSha": "838d596987633e3a25b6e8c2c02aeaf2c3330e72",
  "name": "Build Documentation",
  "number": 45328,
  "startedAt": "2025-07-25T07:01:01Z",
  "status": "completed",
  "updatedAt": "2025-07-25T07:03:29Z",
  "url": "https://github.com/apache/nuttx/actions/runs/16515933461",
  "workflowDatabaseId": 904372,
  "workflowName": "Build Documentation"
}
