{
  "conclusion": "success",
  "createdAt": "2025-08-01T05:10:53Z",
  "databaseId": 16666871516,
  "displayTitle": "sched: Fix smp scheduling",
  "event": "pull_request",
  "headBranch": "fix_smp_scheduling",
  "headSha": "421211f6693aded1e638b481674db5478aa45f7a",
  "name": "Build",
  "number": 49515,
  "startedAt": "2025-08-01T05:10:53Z",
  "status": "completed",
  "updatedAt": "2025-08-01T07:58:30Z",
  "url": "https://github.com/apache/nuttx/actions/runs/16666871516",
  "workflowDatabaseId": 908549,
  "workflowName": "Build"
}
