{
  "conclusion": "success",
  "createdAt": "2025-08-29T15:15:47Z",
  "databaseId": 17327606275,
  "displayTitle": "sched/signal/sig_dispatch.c: Correct signal dispatch to specific thread",
  "event": "pull_request_target",
  "headBranch": "fix_signal_not_delivered",
  "headSha": "740b7de8df05b99e4d45668f72e6110edb363f6f",
  "name": "Pull Request Labeler",
  "number": 7825,
  "startedAt": "2025-08-29T15:15:47Z",
  "status": "completed",
  "updatedAt": "2025-08-29T15:16:20Z",
  "url": "https://github.com/apache/nuttx/actions/runs/17327606275",
  "workflowDatabaseId": 118322422,
  "workflowName": "Pull Request Labeler"
}
