{
  "conclusion": "cancelled",
  "createdAt": "2025-09-15T06:01:46Z",
  "databaseId": 17723588712,
  "displayTitle": "drivers/syslog: add light-weight, synchronous, unicast and lowlevel console output syslog function",
  "event": "pull_request",
  "headBranch": "add_syn_unicast_syslog",
  "headSha": "4bc6e576a1a297d98c879924efa6fade5a1b9b3d",
  "name": "Build",
  "number": 50057,
  "startedAt": "2025-09-15T06:01:46Z",
  "status": "completed",
  "updatedAt": "2025-09-15T06:05:44Z",
  "url": "https://github.com/apache/nuttx/actions/runs/17723588712",
  "workflowDatabaseId": 908549,
  "workflowName": "Build"
}
