{
  "attempt": 1,
  "conclusion": "success",
  "createdAt": "2025-09-19T07:48:32Z",
  "databaseId": 17852069798,
  "displayTitle": "arch/arm64/imx9: Add ele commit message",
  "event": "pull_request",
  "headBranch": "add_nxp93_ele_commit_message",
  "headSha": "6d92e852a1ac6ac80d07b4e6ee672509f5e6147d",
  "name": "Lint",
  "number": 35313,
  "startedAt": "2025-09-19T07:48:32Z",
  "status": "completed",
  "updatedAt": "2025-09-19T07:50:36Z",
  "url": "https://github.com/apache/nuttx/actions/runs/17852069798",
  "workflowDatabaseId": 4260298,
  "workflowName": "Lint"
}
