{
  "attempt": 1,
  "conclusion": "success",
  "createdAt": "2025-09-23T03:01:48Z",
  "databaseId": 17934507555,
  "displayTitle": "sched/task: Provide a task stack overflow check mechanism in task context switch and task exit",
  "event": "pull_request",
  "headBranch": "add_task_overflow_check",
  "headSha": "a693fd11615f20cd873b59b3481a42ed917addab",
  "name": "Build Documentation",
  "number": 45554,
  "startedAt": "2025-09-23T03:01:48Z",
  "status": "completed",
  "updatedAt": "2025-09-23T03:04:17Z",
  "url": "https://github.com/apache/nuttx/actions/runs/17934507555",
  "workflowDatabaseId": 904372,
  "workflowName": "Build Documentation"
}
