{
  "attempt": 1,
  "conclusion": "success",
  "createdAt": "2025-09-28T08:24:40Z",
  "databaseId": 18071690264,
  "displayTitle": "exclude cxx-oot-build test",
  "event": "pull_request",
  "headBranch": "use-updated-nuttx-add-subdir",
  "headSha": "ad972b0e38541bf5e2f69d6e35bca87c2ed720e9",
  "name": "Lint",
  "number": 5710,
  "startedAt": "2025-09-28T08:24:40Z",
  "status": "completed",
  "updatedAt": "2025-09-28T08:26:20Z",
  "url": "https://github.com/apache/nuttx-apps/actions/runs/18071690264",
  "workflowDatabaseId": 4585365,
  "workflowName": "Lint"
}
