{
  "attempt": 1,
  "conclusion": "failure",
  "createdAt": "2025-10-01T14:35:35Z",
  "databaseId": 18165717764,
  "displayTitle": "drivers/syslog: add light-weight, synchronous, unicast and lowlevel console output syslog function",
  "event": "pull_request",
  "headBranch": "add_syn_unicast_syslog",
  "headSha": "e8785b1676263cc551a3672fb12fe0a48cfa8d68",
  "name": "Build",
  "number": 50352,
  "startedAt": "2025-10-01T14:35:35Z",
  "status": "completed",
  "updatedAt": "2025-10-01T16:59:23Z",
  "url": "https://github.com/apache/nuttx/actions/runs/18165717764",
  "workflowDatabaseId": 908549,
  "workflowName": "Build"
}
