{
  "conclusion": "success",
  "createdAt": "2025-11-27T01:42:45Z",
  "databaseId": 19722537671,
  "displayTitle": "apps: decouple signal support",
  "event": "pull_request",
  "headBranch": "apps_signal_decouple",
  "headSha": "15ca04b3821792fef84241d21e9189f68e982213",
  "name": "Check",
  "number": 6507,
  "startedAt": "2025-11-27T01:42:45Z",
  "status": "completed",
  "updatedAt": "2025-11-27T01:43:34Z",
  "url": "https://github.com/apache/nuttx-apps/actions/runs/19722537671",
  "workflowDatabaseId": 904465,
  "workflowName": "Check"
}
