{
  "conclusion": "success",
  "createdAt": "2025-12-09T15:39:05Z",
  "databaseId": 20069242007,
  "displayTitle": "netdev_upperhalf: convert Kconfig to variable",
  "event": "pull_request",
  "headBranch": "upstream-10",
  "headSha": "977c8c16b2ec3051eda84bd1da5bcd0c89273fdb",
  "name": "Build",
  "number": 51202,
  "startedAt": "2025-12-09T15:39:05Z",
  "status": "completed",
  "updatedAt": "2025-12-09T18:52:00Z",
  "url": "https://github.com/apache/nuttx/actions/runs/20069242007",
  "workflowDatabaseId": 908549,
  "workflowName": "Build"
}
