{
  "conclusion": "success",
  "createdAt": "2025-12-11T05:20:11Z",
  "databaseId": 20122867722,
  "displayTitle": "add a reference count to the TCB to prevent it from being deleted.",
  "event": "pull_request",
  "headBranch": "apache_6",
  "headSha": "c01d9d1a5955830e2b911d448f155e86dadb5817",
  "name": "Lint",
  "number": 5834,
  "startedAt": "2025-12-11T05:20:11Z",
  "status": "completed",
  "updatedAt": "2025-12-11T05:21:52Z",
  "url": "https://github.com/apache/nuttx-apps/actions/runs/20122867722",
  "workflowDatabaseId": 4585365,
  "workflowName": "Lint"
}
