{
  "conclusion": "success",
  "createdAt": "2025-12-18T13:02:28Z",
  "databaseId": 20337841064,
  "displayTitle": "apps/netutils: Modify the MQTT compilation file to enable MQTT testing",
  "event": "pull_request",
  "headBranch": "master2",
  "headSha": "025ba865b69861b8f6efe800673f4d58777f6f6d",
  "name": "Lint",
  "number": 5852,
  "startedAt": "2025-12-18T13:02:28Z",
  "status": "completed",
  "updatedAt": "2025-12-18T13:04:31Z",
  "url": "https://github.com/apache/nuttx-apps/actions/runs/20337841064",
  "workflowDatabaseId": 4585365,
  "workflowName": "Lint"
}
