{
  "attempt": 1,
  "conclusion": "success",
  "createdAt": "2025-12-21T14:33:11Z",
  "databaseId": 20411296784,
  "displayTitle": "arch/arm: Aligned Cmake with Make",
  "event": "pull_request",
  "headBranch": "simbit18-alignment",
  "headSha": "d86e73ab9e0876d0c691f2e2aa0e97666b0cdaba",
  "name": "Build",
  "number": 51512,
  "startedAt": "2025-12-21T14:33:11Z",
  "status": "completed",
  "updatedAt": "2025-12-21T16:35:11Z",
  "url": "https://github.com/apache/nuttx/actions/runs/20411296784",
  "workflowDatabaseId": 908549,
  "workflowName": "Build"
}
