{
  "conclusion": "success",
  "createdAt": "2025-12-22T03:21:32Z",
  "databaseId": 20420729200,
  "displayTitle": "power/battery: battery gauge driver support",
  "event": "pull_request",
  "headBranch": "battery",
  "headSha": "7943bc9501f0960061a0a999a78652f9a8426e41",
  "name": "Build Documentation",
  "number": 46003,
  "startedAt": "2025-12-22T03:21:32Z",
  "status": "completed",
  "updatedAt": "2025-12-22T03:23:53Z",
  "url": "https://github.com/apache/nuttx/actions/runs/20420729200",
  "workflowDatabaseId": 904372,
  "workflowName": "Build Documentation"
}
