{
  "conclusion": "success",
  "createdAt": "2025-12-22T06:05:11Z",
  "databaseId": 20423380702,
  "displayTitle": "net/netdev: allow stack to send/receive when running",
  "event": "pull_request",
  "headBranch": "48967",
  "headSha": "4d01653d1cae41b7ec6eb8b292bf31a23a427ba9",
  "name": "Check",
  "number": 39900,
  "startedAt": "2025-12-22T06:05:11Z",
  "status": "completed",
  "updatedAt": "2025-12-22T06:05:57Z",
  "url": "https://github.com/apache/nuttx/actions/runs/20423380702",
  "workflowDatabaseId": 904371,
  "workflowName": "Check"
}
