{
  "attempt": 1,
  "conclusion": "success",
  "createdAt": "2025-12-24T02:22:21Z",
  "databaseId": 20476430903,
  "displayTitle": "net/tcp: resolve reconnection issues when connection failed due to rejection",
  "event": "pull_request",
  "headBranch": "2715",
  "headSha": "710565438dbd19c50ac515e98551585a432eb7ee",
  "name": "Lint",
  "number": 36889,
  "startedAt": "2025-12-24T02:22:21Z",
  "status": "completed",
  "updatedAt": "2025-12-24T02:24:29Z",
  "url": "https://github.com/apache/nuttx/actions/runs/20476430903",
  "workflowDatabaseId": 4260298,
  "workflowName": "Lint"
}
