{
  "attempt": 1,
  "conclusion": "success",
  "createdAt": "2025-12-25T04:36:24Z",
  "databaseId": 20499055703,
  "displayTitle": "net/bufpool: fix typo",
  "event": "pull_request",
  "headBranch": "upstream-9",
  "headSha": "3321142c160f0d2dc4b12654fa552ea9c67c0ebe",
  "name": "Lint",
  "number": 36930,
  "startedAt": "2025-12-25T04:36:24Z",
  "status": "completed",
  "updatedAt": "2025-12-25T04:38:31Z",
  "url": "https://github.com/apache/nuttx/actions/runs/20499055703",
  "workflowDatabaseId": 4260298,
  "workflowName": "Lint"
}
