{
  "conclusion": "success",
  "createdAt": "2026-01-05T02:08:39Z",
  "databaseId": 20702977364,
  "displayTitle": "drivers/adc: Use mutexlock to replace critical section protection",
  "event": "pull_request",
  "headBranch": "adc",
  "headSha": "ae58d6b31c7ed02617978846c49c68feac8a3033",
  "name": "Check",
  "number": 40309,
  "startedAt": "2026-01-05T02:08:39Z",
  "status": "completed",
  "updatedAt": "2026-01-05T02:09:23Z",
  "url": "https://github.com/apache/nuttx/actions/runs/20702977364",
  "workflowDatabaseId": 904371,
  "workflowName": "Check"
}
