{
  "attempt": 1,
  "conclusion": "success",
  "createdAt": "2026-01-05T14:51:35Z",
  "databaseId": 20719133022,
  "displayTitle": "[EXPERIMENTAL]sched/hrtimer: hrtimer state machine improvement for SMP cases",
  "event": "pull_request",
  "headBranch": "refine_hrtimer",
  "headSha": "5735bb1be84fa125d5f4a61181ba902c9b88c30a",
  "name": "Check",
  "number": 40350,
  "startedAt": "2026-01-05T14:51:35Z",
  "status": "completed",
  "updatedAt": "2026-01-05T14:52:16Z",
  "url": "https://github.com/apache/nuttx/actions/runs/20719133022",
  "workflowDatabaseId": 904371,
  "workflowName": "Check"
}
