{
  "attempt": 2,
  "conclusion": "failure",
  "createdAt": "2026-01-12T06:52:26Z",
  "databaseId": 20910559536,
  "displayTitle": "libs: Add support for latest LLVM LIBCXX and LIBCXXABI version 21.1.8",
  "event": "pull_request",
  "headBranch": "feature/add-support-for-latest-libcxx-and-libcxxabi",
  "headSha": "0b3dd3004c9e29f9af9ba2760e95bb1d01de3957",
  "name": "Build",
  "number": 52205,
  "startedAt": "2026-01-12T07:34:28Z",
  "status": "completed",
  "updatedAt": "2026-01-12T08:00:44Z",
  "url": "https://github.com/apache/nuttx/actions/runs/20910559536",
  "workflowDatabaseId": 908549,
  "workflowName": "Build"
}
