{
  "attempt": 1,
  "conclusion": "success",
  "createdAt": "2026-01-12T12:12:37Z",
  "databaseId": 20918924158,
  "displayTitle": "if_ether.h: add the definition of ETH_P_TSN",
  "event": "pull_request_target",
  "headBranch": "upstream-3",
  "headSha": "cf4d6202a92b025cae1ddc51ba9873073bbc5a09",
  "name": "Pull Request Labeler",
  "number": 10282,
  "startedAt": "2026-01-12T12:12:37Z",
  "status": "completed",
  "updatedAt": "2026-01-12T12:13:04Z",
  "url": "https://github.com/apache/nuttx/actions/runs/20918924158",
  "workflowDatabaseId": 118322422,
  "workflowName": "Pull Request Labeler"
}
