{
  "conclusion": "success",
  "createdAt": "2026-01-13T08:11:06Z",
  "databaseId": 20949420272,
  "displayTitle": "libs/libs: fix wqueue config typo",
  "event": "pull_request",
  "headBranch": "wqueue_fix_typo_error",
  "headSha": "c1c6adb2a939018d778a2a9338e069748afd8885",
  "name": "Check",
  "number": 40598,
  "startedAt": "2026-01-13T08:11:06Z",
  "status": "completed",
  "updatedAt": "2026-01-13T08:17:33Z",
  "url": "https://github.com/apache/nuttx/actions/runs/20949420272",
  "workflowDatabaseId": 904371,
  "workflowName": "Check"
}
