{
  "conclusion": "success",
  "createdAt": "2026-01-16T12:20:02Z",
  "databaseId": 21066420759,
  "displayTitle": "tricore/csrm: bringup cpucs in tricore",
  "event": "pull_request",
  "headBranch": "tricore-csrm-bringup",
  "headSha": "709624d42fadc3bfc20bebb73141015a13f921f2",
  "name": "Lint",
  "number": 37738,
  "startedAt": "2026-01-16T12:20:02Z",
  "status": "completed",
  "updatedAt": "2026-01-16T12:22:04Z",
  "url": "https://github.com/apache/nuttx/actions/runs/21066420759",
  "workflowDatabaseId": 4260298,
  "workflowName": "Lint"
}
