{
  "attempt": 1,
  "conclusion": "success",
  "createdAt": "2026-01-17T04:50:41Z",
  "databaseId": 21088724086,
  "displayTitle": "tricore/csrm: bringup cpucs in tricore",
  "event": "pull_request",
  "headBranch": "tricore-csrm-bringup",
  "headSha": "62c17f5543848694c7fc636296283079b7364721",
  "name": "Lint",
  "number": 37765,
  "startedAt": "2026-01-17T04:50:41Z",
  "status": "completed",
  "updatedAt": "2026-01-17T04:52:50Z",
  "url": "https://github.com/apache/nuttx/actions/runs/21088724086",
  "workflowDatabaseId": 4260298,
  "workflowName": "Lint"
}
