{
  "attempt": 1,
  "conclusion": "success",
  "createdAt": "2026-01-21T14:46:30Z",
  "databaseId": 21213904473,
  "displayTitle": "sched/irq: avoid casting from signed int to unsigned int",
  "event": "pull_request_target",
  "headBranch": "coverity_6174390",
  "headSha": "3f7eff4b1ec3988f0a9b021b24f066c207245c21",
  "name": "Pull Request Labeler",
  "number": 10874,
  "startedAt": "2026-01-21T14:46:30Z",
  "status": "completed",
  "updatedAt": "2026-01-21T14:47:05Z",
  "url": "https://github.com/apache/nuttx/actions/runs/21213904473",
  "workflowDatabaseId": 118322422,
  "workflowName": "Pull Request Labeler"
}
