{
  "attempt": 1,
  "conclusion": "success",
  "createdAt": "2026-01-21T13:31:00Z",
  "databaseId": 21211449005,
  "displayTitle": "add a reference count to the TCB to prevent it from being deleted.",
  "event": "pull_request",
  "headBranch": "apache_6",
  "headSha": "a3ce4d60a796065f3a07b30e3dd833fbdd14ce7d",
  "name": "Check",
  "number": 6860,
  "startedAt": "2026-01-21T13:31:00Z",
  "status": "completed",
  "updatedAt": "2026-01-21T13:31:57Z",
  "url": "https://github.com/apache/nuttx-apps/actions/runs/21211449005",
  "workflowDatabaseId": 904465,
  "workflowName": "Check"
}
