{
  "attempt": 1,
  "conclusion": "success",
  "createdAt": "2026-01-24T08:20:55Z",
  "databaseId": 21312114606,
  "displayTitle": "arm64: add protected mode support and SMP improvements",
  "event": "pull_request",
  "headBranch": "apache_arm64_support_protectbuild_1",
  "headSha": "f82c60efa44c4eedbfb55ecca17f0f45829ee64e",
  "name": "Lint",
  "number": 38161,
  "startedAt": "2026-01-24T08:20:55Z",
  "status": "completed",
  "updatedAt": "2026-01-24T08:23:03Z",
  "url": "https://github.com/apache/nuttx/actions/runs/21312114606",
  "workflowDatabaseId": 4260298,
  "workflowName": "Lint"
}
