{
  "conclusion": "success",
  "createdAt": "2026-01-27T04:04:05Z",
  "databaseId": 21384072115,
  "displayTitle": "!drivers/note: unify note ioctl command",
  "event": "pull_request",
  "headBranch": "unify-note-ioctl",
  "headSha": "25922291a69c327cc2bd0d280a934c3efcebf513",
  "name": "Lint",
  "number": 38321,
  "startedAt": "2026-01-27T04:04:05Z",
  "status": "completed",
  "updatedAt": "2026-01-27T04:06:10Z",
  "url": "https://github.com/apache/nuttx/actions/runs/21384072115",
  "workflowDatabaseId": 4260298,
  "workflowName": "Lint"
}
