{
  "attempt": 1,
  "conclusion": "success",
  "createdAt": "2026-01-27T08:11:48Z",
  "databaseId": 21389501510,
  "displayTitle": "sched/signal: Optimize code logic",
  "event": "pull_request",
  "headBranch": "up_schedule_sigact",
  "headSha": "72f264127eae8ea5c764f369703b106821524a27",
  "name": "Lint",
  "number": 38347,
  "startedAt": "2026-01-27T08:11:48Z",
  "status": "completed",
  "updatedAt": "2026-01-27T08:13:59Z",
  "url": "https://github.com/apache/nuttx/actions/runs/21389501510",
  "workflowDatabaseId": 4260298,
  "workflowName": "Lint"
}
