{
  "attempt": 1,
  "conclusion": "success",
  "createdAt": "2026-01-27T06:47:24Z",
  "databaseId": 21387453037,
  "displayTitle": "sched/irq: Avoid negative array index in irqchain_dispatch",
  "event": "pull_request_target",
  "headBranch": "irq_chain_negative_clean",
  "headSha": "b8a5b61af15da42b3d9b2724f8b7a61233df6192",
  "name": "Pull Request Labeler",
  "number": 11197,
  "startedAt": "2026-01-27T06:47:24Z",
  "status": "completed",
  "updatedAt": "2026-01-27T06:47:58Z",
  "url": "https://github.com/apache/nuttx/actions/runs/21387453037",
  "workflowDatabaseId": 118322422,
  "workflowName": "Pull Request Labeler"
}
