{
  "conclusion": "success",
  "createdAt": "2026-01-28T02:31:44Z",
  "databaseId": 21422586889,
  "displayTitle": "sched_setpriority: Consolidate return statements for MISRA HIS compliance",
  "event": "pull_request_target",
  "headBranch": "apache_sched_setpriority_coverity_HIS_metric_violation_RETURN",
  "headSha": "d96b3602a3ae1216fe1f84ef9634b8899ef87efc",
  "name": "Pull Request Labeler",
  "number": 11235,
  "startedAt": "2026-01-28T02:31:44Z",
  "status": "completed",
  "updatedAt": "2026-01-28T02:32:12Z",
  "url": "https://github.com/apache/nuttx/actions/runs/21422586889",
  "workflowDatabaseId": 118322422,
  "workflowName": "Pull Request Labeler"
}
