{
  "conclusion": "success",
  "createdAt": "2026-01-29T08:10:20Z",
  "databaseId": 21470520190,
  "displayTitle": "boards/sim/crypto: enable cmocka testing framework",
  "event": "pull_request_target",
  "headBranch": "sim-crypto-testing",
  "headSha": "186e2b91d5348ac517ec0623ed33b84e4671a4ca",
  "name": "Pull Request Labeler",
  "number": 11341,
  "startedAt": "2026-01-29T08:10:20Z",
  "status": "completed",
  "updatedAt": "2026-01-29T08:10:47Z",
  "url": "https://github.com/apache/nuttx/actions/runs/21470520190",
  "workflowDatabaseId": 118322422,
  "workflowName": "Pull Request Labeler"
}
