{
  "conclusion": "success",
  "createdAt": "2026-02-04T20:16:11Z",
  "databaseId": 21686829996,
  "displayTitle": "arch/arm/stm32h7: fix sdcan clock, ILS register and ID",
  "event": "pull_request",
  "headBranch": "up_st7796",
  "headSha": "da1b3b4875d700cb18e741fa16de39fb4ca21475",
  "name": "Build",
  "number": 53480,
  "startedAt": "2026-02-04T20:16:11Z",
  "status": "completed",
  "updatedAt": "2026-02-04T22:25:45Z",
  "url": "https://github.com/apache/nuttx/actions/runs/21686829996",
  "workflowDatabaseId": 908549,
  "workflowName": "Build"
}
