{
  "conclusion": "failure",
  "createdAt": "2026-02-15T21:38:50Z",
  "databaseId": 22043535388,
  "displayTitle": "!interpreters: Align naming of Kconfig options",
  "event": "pull_request",
  "headBranch": "interpreter-interpreters",
  "headSha": "275d64249d260f701c6b6b8cca3cbe032c363f18",
  "name": "Check",
  "number": 6972,
  "startedAt": "2026-02-15T21:38:50Z",
  "status": "completed",
  "updatedAt": "2026-02-15T21:39:39Z",
  "url": "https://github.com/apache/nuttx-apps/actions/runs/22043535388",
  "workflowDatabaseId": 904465,
  "workflowName": "Check"
}
