{
  "attempt": 1,
  "conclusion": "success",
  "createdAt": "2026-02-24T08:36:25Z",
  "databaseId": 22342954806,
  "displayTitle": "arch/risc-v/espressif: Fix SHA errors",
  "event": "pull_request",
  "headBranch": "bugfix/esp_crypto_bugfix",
  "headSha": "3a79d7c2550d54781fe2bc205abe3da0ea4a3905",
  "name": "Build",
  "number": 53682,
  "startedAt": "2026-02-24T08:36:25Z",
  "status": "completed",
  "updatedAt": "2026-02-24T11:55:00Z",
  "url": "https://github.com/apache/nuttx/actions/runs/22342954806",
  "workflowDatabaseId": 908549,
  "workflowName": "Build"
}
