{
  "conclusion": "success",
  "createdAt": "2026-02-27T10:37:21Z",
  "databaseId": 22482815242,
  "displayTitle": "Set Pull Request Labels",
  "event": "workflow_run",
  "headBranch": "master",
  "headSha": "635f64ebb8afa62792bb82145b91f01e41e57fdb",
  "name": "Set Pull Request Labels",
  "number": 141,
  "startedAt": "2026-02-27T10:37:21Z",
  "status": "completed",
  "updatedAt": "2026-02-27T10:37:30Z",
  "url": "https://github.com/apache/nuttx/actions/runs/22482815242",
  "workflowDatabaseId": 235202887,
  "workflowName": "Set Pull Request Labels"
}
