{
  "conclusion": "cancelled",
  "createdAt": "2026-03-09T20:07:05Z",
  "databaseId": 22872479391,
  "displayTitle": "fs/mnemofs: Add portable bit primitives and cleanup hash functions",
  "event": "pull_request",
  "headBranch": "mnemofs-bit-pr",
  "headSha": "7d89731140755699ea188cb532e4b3447755f9e0",
  "name": "Build",
  "number": 53880,
  "startedAt": "2026-03-09T20:19:13Z",
  "status": "completed",
  "updatedAt": "2026-03-09T20:30:15Z",
  "url": "https://github.com/apache/nuttx/actions/runs/22872479391",
  "workflowDatabaseId": 908549,
  "workflowName": "Build"
}
