{
  "conclusion": "success",
  "createdAt": "2026-03-17T22:36:27Z",
  "databaseId": 23219646883,
  "displayTitle": "drivers/mtd/ftl: honor O_DIRECT flag, remove bootloader write buffering",
  "event": "pull_request",
  "headBranch": "fix/ftl-odirect-writebuffer",
  "headSha": "3f43c852c5bbe5d2e4323835a40bb883274306d0",
  "name": "Lint",
  "number": 39221,
  "startedAt": "2026-03-17T22:36:27Z",
  "status": "completed",
  "updatedAt": "2026-03-17T22:38:40Z",
  "url": "https://github.com/apache/nuttx/actions/runs/23219646883",
  "workflowDatabaseId": 4260298,
  "workflowName": "Lint"
}
