{
  "conclusion": "success",
  "createdAt": "2026-03-23T16:24:13Z",
  "databaseId": 23448021035,
  "displayTitle": "add nxscope examples and doc",
  "event": "pull_request",
  "headBranch": "nxscope_upstream",
  "headSha": "b41a71fb40101956e82959b78c58d68624900479",
  "name": "Pull Request Labeler",
  "number": 12154,
  "startedAt": "2026-03-23T16:24:13Z",
  "status": "completed",
  "updatedAt": "2026-03-23T16:24:23Z",
  "url": "https://github.com/apache/nuttx/actions/runs/23448021035",
  "workflowDatabaseId": 118322422,
  "workflowName": "Pull Request Labeler"
}
