{
  "conclusion": "success",
  "createdAt": "2026-03-27T08:06:45Z",
  "databaseId": 23637037404,
  "displayTitle": "{bp-18488} netdev/netdev_ioctl: log in hex mode for ioctl cmd",
  "event": "pull_request",
  "headBranch": "bp-18488",
  "headSha": "6a73ca83cc25699c2f711c92ffe7ad554abbe362",
  "name": "Check",
  "number": 42440,
  "startedAt": "2026-03-27T08:06:45Z",
  "status": "completed",
  "updatedAt": "2026-03-27T08:07:24Z",
  "url": "https://github.com/apache/nuttx/actions/runs/23637037404",
  "workflowDatabaseId": 904371,
  "workflowName": "Check"
}
