{
  "conclusion": "startup_failure",
  "createdAt": "2026-03-27T08:26:18Z",
  "databaseId": 23637672483,
  "displayTitle": "Build",
  "event": "pull_request",
  "headBranch": "bp-18579",
  "headSha": "5a920617819f0657c18ebbc3cf2144ca5877b3e4",
  "name": "Build",
  "number": 54119,
  "startedAt": "2026-03-27T08:26:18Z",
  "status": "completed",
  "updatedAt": "2026-03-27T08:26:18Z",
  "url": "https://github.com/apache/nuttx/actions/runs/23637672483",
  "workflowDatabaseId": 908549,
  "workflowName": "Build"
}
