{
  "conclusion": "success",
  "createdAt": "2026-03-31T11:49:09Z",
  "databaseId": 23795731163,
  "displayTitle": "Set Pull Request Labels",
  "event": "workflow_run",
  "headBranch": "master",
  "headSha": "073df9d1dec8d569e971e39c9dc71504f40836ea",
  "name": "Set Pull Request Labels",
  "number": 57,
  "startedAt": "2026-03-31T11:49:09Z",
  "status": "completed",
  "updatedAt": "2026-03-31T11:49:20Z",
  "url": "https://github.com/apache/nuttx-apps/actions/runs/23795731163",
  "workflowDatabaseId": 237587246,
  "workflowName": "Set Pull Request Labels"
}
