{
  "conclusion": "",
  "createdAt": "2026-04-02T21:40:27Z",
  "databaseId": 23923294452,
  "displayTitle": "espressif/rmt: replace rmtchar with arch-specific lirc adapter",
  "event": "pull_request",
  "headBranch": "espressif-rmt-lirc-refactor",
  "headSha": "67d8a8af9c88baa753c48ea8180573e5b0c1f7bd",
  "name": "Build",
  "number": 54226,
  "startedAt": "2026-04-02T21:40:27Z",
  "status": "queued",
  "updatedAt": "2026-04-02T21:42:14Z",
  "url": "https://github.com/apache/nuttx/actions/runs/23923294452",
  "workflowDatabaseId": 908549,
  "workflowName": "Build"
}
