{
"timestamp": "2026-04-06T10:13:48",
"arch": "sim",
"subarch": "sim",
"group": "sim-02",
"board": "sim",
"config": "nxcamera",
"build_score": 0,
"version": "3",
"url": "https://github.com/apache/nuttx/actions/runs/24026963105/job/70067589616#step:10:602",
"msg": "gzip: stdin: not in gzip format \n tar: Child returned status 1 \n tar: Error is not recoverable: exiting now \n make[3]: *** [Makefile:34: libyuv.tar.gz] Error 2 \n make[3]: Target 'context' not remade because of errors. \n make[2]: *** [Makefile:57: /github/workspace/sources/apps/graphics/libyuv_context] Error 2 \n make[2]: Target 'context_all' not remade because of errors. \n make[1]: *** [Makefile:187: context] Error 2 \n make: *** [tools/Unix.mk:467: /github/workspace/sources/apps/.context] Error 2 \n "
}
